[
  {
      "name": "Everything - Testing",
      "description": "Test function to test all field types",
      "type": "transformation",
      "code": "everything/everything.js",
      "ui_config" : "everything/ui_config.json"
  },
  {
      "name": "PII Hashing",
      "description": "Hashes specified PII data before event enrichments",
      "type": "transformation",
      "code": "pii_hashing/pii_hashing.js",
      "ui_config" : "pii_hashing/ui_config.json"
  },
  {
      "name": "PII Encrypting",
      "description": "Encrypts specified PII data with a secret key before event enrichments",
      "type": "transformation",
      "code": "pii_encrypting/pii_encrypting.js",
      "ui_config" : "pii_encrypting/ui_config.json"
  },
  {
      "name": "Visitor Example",
      "description": "This is just an example, it doesnt really do anything",
      "type": "visitor",
      "code": "visitor_example/visitor_example.js",
      "ui_config" : "visitor_example/ui_config.json"
  },
  {
      "name": "Event Example",
      "description": "This is just an example, it doesnt really do anything",
      "type": "event",
      "code": "event_example/event_example.js",
      "ui_config" : "event_example/ui_config.json"
  }
]
